LICENSE
MANIFEST.in
README.md
changelog.md
setup.py
lidl_receipts_de/__init__.py
papermerge_meta_plugin_lidl_receipts_de.egg-info/PKG-INFO
papermerge_meta_plugin_lidl_receipts_de.egg-info/SOURCES.txt
papermerge_meta_plugin_lidl_receipts_de.egg-info/dependency_links.txt
papermerge_meta_plugin_lidl_receipts_de.egg-info/top_level.txt
test/test_lidl.py
test/data/doc-361-page-1.hocr
test/data/doc-422-page-2.hocr
test/data/doc-422-page-3.hocr
test/data/doc-64-page-1.hocr
test/data/lidl-1.hocr
test/data/lidl-2.hocr
test/data/lidl-3.hocr
test/data/lidl-5.hocr
test/data/lidl-7.hocr
test/data/lidl-8.hocr