Metadata-Version: 2.1
Name: papermerge-meta-plugin-lidl-receipts-de
Version: 0.3.0
Summary: Metadata plugin for lidl receipts (used in Germany)
Home-page: https://github.com/papermerge/lidl-receipts-de
Author: Eugen Ciur
Author-email: eugen@papermerge.com
License: Apache 2.0 License
Keywords: metadata,papermerge,plugin,receipts
Platform: UNKNOWN
Classifier: Programming Language :: Python :: 3
Classifier: License :: OSI Approved :: Apache Software License
Classifier: Operating System :: OS Independent
Requires-Python: >=3.7
